{
  "_regime_context": {
    "regime": "Neutral \u2014 Leaning Risk-Off",
    "score": -0.06,
    "signal_summary": "- Term Premium: z=+1.00 ()\n- Consumer Sentiment (Michigan): z=-0.82 ()\n- Credit Spreads (HY vs Treasuries): z=-0.79 ()\n- Commodity Trend (Oil + Copper): z=+0.78 ()\n- VIX (Equity Volatility): z=-0.66 ()\n- Market Breadth (RSP/SPY): z=+0.66 ()\n- Corporate CAPEX vs Liquidity: z=+0.60 ()\n- Equity Trend (S&P, Nasdaq, Dow): z=-0.58 ()\n- Fear & Greed Index: 8/100 \u2014 Extreme Fear (contrarian)",
    "quadrant": "Stagflation"
  },
  "_regime_context_ts": {
    "__datetime__": "2026-04-01T15:03:54.872179"
  },
  "_rp_plays_result": {
    "sectors": [],
    "stocks": [],
    "bonds": [],
    "rationale": ""
  },
  "_rp_plays_last_tier": "\u26a1 Freeloader Mode",
  "_rate_path_probs": [
    {
      "scenario": "hold",
      "prob": 0.665526225301367,
      "implied_rate": 3.6399993896484375,
      "source": "yfinance"
    },
    {
      "scenario": "cut_25",
      "prob": 0.1659515597053382,
      "implied_rate": 3.6399993896484375,
      "source": "yfinance"
    },
    {
      "scenario": "cut_50",
      "prob": 0.002572906134776094,
      "implied_rate": 3.6399993896484375,
      "source": "yfinance"
    },
    {
      "scenario": "hike_25",
      "prob": 0.16594930885851863,
      "implied_rate": 3.6399993896484375,
      "source": "yfinance"
    }
  ],
  "_current_events_digest": "In the current neutral, risk-off macro regime with a stagflationary bias, recent events confirm the dominant narrative of supply chain disruptions and rising costs. The declaration of force majeure by AirGas on helium shipments due to Qatar production collapses, as highlighted by zerohedge, exacerbates concerns over critical component shortages, particularly for Taiwan's chip industry, which relies heavily on helium for production. Meanwhile, Japan's bond market yields are rising sharply, with the 10-year yield reaching 2.37%, signaling a bearish outlook. These developments underscore the potential for further inflationary pressures and economic instability, aligning with the regime's stagflationary characteristics.",
  "_current_events_digest_ts": {
    "__datetime__": "2026-04-01T15:03:58.176550"
  },
  "_current_events_engine": "\u26a1 Freeloader Mode",
  "_tactical_context": {
    "tactical_score": 53,
    "label": "Neutral / Hold",
    "action_bias": "Mixed short-term signals. Hold existing positions; await a clearer setup.",
    "signals": [
      {
        "Signal": "VIX Level + 5d Trend",
        "Value": "24.3 (-1.0 5d)",
        "Score": -0.261,
        "Direction": "Risk-Off"
      },
      {
        "Signal": "VIX Term Structure (VIX/VIX3M)",
        "Value": "0.968",
        "Score": 0.213,
        "Direction": "Risk-On"
      },
      {
        "Signal": "SPY vs 20d/50d MA",
        "Value": "-0.4%/20d  -2.8%/50d",
        "Score": 0.019,
        "Direction": "True Neutral"
      },
      {
        "Signal": "SPY Momentum (5d vs 20d ROC)",
        "Value": "5d -0.0%  20d -3.9%",
        "Score": 0.183,
        "Direction": "Neutral \u2014 Leaning Risk-On"
      },
      {
        "Signal": "Breadth Trend (RSP/SPY 5d)",
        "Value": "+0.25% 5d",
        "Score": 0.252,
        "Direction": "Risk-On"
      },
      {
        "Signal": "VIX Curve (9D/VIX/3M/6M)",
        "Value": "9D:22.9 VIX:24.3 3M:25.1 6M:26.5",
        "Score": 0.317,
        "Direction": "Risk-On"
      },
      {
        "Signal": "CBOE SKEW (Tail Risk)",
        "Value": "145.4 (+4.6 5d)",
        "Score": -1.0,
        "Direction": "Risk-Off"
      },
      {
        "Signal": "Fear & Greed (Contrarian)",
        "Value": "8 \u2014 Extreme Fear (-6 7d)",
        "Score": 0.84,
        "Direction": "Risk-On"
      },
      {
        "Signal": "AAII Sentiment (Contrarian)",
        "Value": "N/A",
        "Score": 0.0,
        "Direction": "True Neutral"
      }
    ]
  },
  "_tactical_context_ts": {
    "__datetime__": "2026-04-01T15:03:54.872185"
  },
  "_tactical_analysis": "The combined signal picture suggests a Neutral / Hold stance, with a score of 53/100, reflecting a mixed assessment of short-term risk appetite. The VIX level of 24.3, coupled with a 5-day trend of -1.0, indicates a Risk-Off tone, scoring -0.261. However, this is countered by the VIX term structure (VIX/VIX3M) of 0.968, scoring +0.213, and the VIX Curve (9D/VIX/3M/6M) with values of 22.9/24.3/25.1/26.5, scoring +0.317, both of which lean towards a Risk-On posture. The Fear & Greed index, at 8, signals Extreme Fear and scores +0.840, further supporting a Risk-On view.\n\nThe most dominant signals right now are the CBOE SKEW (Tail Risk) at 145.4, scoring -1.000, and the Fear & Greed index. The CBOE SKEW's high value and significant 5-day increase (+4.6) underscore a heightened concern for tail risk, advising caution. In contrast, the Fear & Greed index's extreme fear reading suggests the market may be oversold, presenting a potential buying opportunity. The interplay between these signals highlights the complexity of the current market environment, where risk aversion and fear coexist with potential oversold conditions.\n\nGiven this setup, the concrete action implication is to maintain a Hold position. With the tactical regime score at 53/100 and the presence of both Risk-Off and Risk-On signals, there's no clear momentum to either add to or reduce positions significantly. The high CBOE SKEW suggests that hedging or maintaining a defensive posture may be prudent, but the Fear & Greed index's extreme fear reading cautions against overly bearish bets. Thus, traders should monitor these signals closely for any shifts that could prompt a change in strategy, focusing on the VIX level, term structure, and sentiment indicators for clues on the next directional move.",
  "_tactical_analysis_ts": {
    "__datetime__": "2026-04-01T15:03:54.872186"
  },
  "_data_quality": {
    "score": 70,
    "label": "Moderate \u2014 some signals stale",
    "stale_market": [
      "DXY"
    ],
    "stale_fred": [
      "sahm",
      "core_pce"
    ],
    "total_signals": 10,
    "fresh_signals": 7
  },
  "_data_quality_ts": {
    "__datetime__": "2026-04-01T15:03:54.872187"
  }
}